InterOptimus/CNID.py
InterOptimus/MPsoap.py
InterOptimus/VaspWorkFlow.py
InterOptimus/__init__.py
InterOptimus/core.py
InterOptimus/equi_term.py
InterOptimus/itworker.py
InterOptimus/matching.py
InterOptimus/mlip.py
InterOptimus/optimize.py
InterOptimus/tool.py
InterOptimus-0.0.4.dist-info/LICENSE
InterOptimus-0.0.4.dist-info/METADATA
InterOptimus-0.0.4.dist-info/WHEEL
InterOptimus-0.0.4.dist-info/top_level.txt
InterOptimus-0.0.4.dist-info/RECORD
