Metadata-Version: 2.1
Name: InterOptimus
Version: 0.0.4
Summary: High througput simulation making crystalline interfaces
Home-page: https://github.com/HouGroup/InterOptimus/
Author: Yaoshu Xie
Author-email: jasonxie@sz.tsinghua.edu.cn
Classifier: Programming Language :: Python :: 3
Classifier: License :: OSI Approved :: MIT License
Classifier: Operating System :: OS Independent
Requires-Python: >=3.10
License-File: LICENSE
Requires-Dist: pymatgen
Requires-Dist: interfacemaster
Requires-Dist: Dscribe
Requires-Dist: scikit-optimize
Requires-Dist: matplotlib
Requires-Dist: atomate
Requires-Dist: fireworks
Requires-Dist: adjustText
Requires-Dist: ipywidgets
Requires-Dist: tqdm
Requires-Dist: mlipdockers
Requires-Dist: mp-api
Requires-Dist: orb-models
Requires-Dist: sevenn
